MANIFEST.in
README.md
setup.py
cellworld_belief/README.md
cellworld_belief/__init__.py
cellworld_belief/arena_component.py
cellworld_belief/belief_state.py
cellworld_belief/belief_state_component.py
cellworld_belief/decreasing_belief_component.py
cellworld_belief/diffusion_component.py
cellworld_belief/directed_difusion_component.py
cellworld_belief/forgetful_belief_component.py
cellworld_belief/gaussian_diffusion_component.py
cellworld_belief/license.txt
cellworld_belief/line_of_sight_component.py
cellworld_belief/map_component.py
cellworld_belief/no_belief_component.py
cellworld_belief/noise_component.py
cellworld_belief/occlussions_component.py
cellworld_belief/proximity_component.py
cellworld_belief/setup.cfg
cellworld_belief/utils.py
cellworld_belief/visibility_component.py
cellworld_belief.egg-info/PKG-INFO
cellworld_belief.egg-info/SOURCES.txt
cellworld_belief.egg-info/dependency_links.txt
cellworld_belief.egg-info/not-zip-safe
cellworld_belief.egg-info/requires.txt
cellworld_belief.egg-info/top_level.txt
cellworld_belief/__pycache__/__init__.cpython-312.pyc
cellworld_belief/__pycache__/arena_component.cpython-312.pyc
cellworld_belief/__pycache__/belief_state.cpython-312.pyc
cellworld_belief/__pycache__/belief_state_component.cpython-312.pyc
cellworld_belief/__pycache__/decreasing_belief_component.cpython-312.pyc
cellworld_belief/__pycache__/diffusion_component.cpython-312.pyc
cellworld_belief/__pycache__/directed_difusion_component.cpython-312.pyc
cellworld_belief/__pycache__/gaussian_diffusion_component.cpython-312.pyc
cellworld_belief/__pycache__/line_of_sight_component.cpython-312.pyc
cellworld_belief/__pycache__/map_component.cpython-312.pyc
cellworld_belief/__pycache__/no_belief_component.cpython-312.pyc
cellworld_belief/__pycache__/noise_component.cpython-312.pyc
cellworld_belief/__pycache__/occlussions_component.cpython-312.pyc
cellworld_belief/__pycache__/proximity_component.cpython-312.pyc
cellworld_belief/__pycache__/utils.cpython-312.pyc
cellworld_belief/__pycache__/visibility_component.cpython-312.pyc