Metadata-Version: 2.1
Name: cellworld_belief
Version: 0.0.35
Author: German Espinosa
Author-email: germanespinosa@gmail.com
License: MIT
Requires-Dist: cellworld_game
Requires-Dist: torch
